stefano_pytgvoip_pyrogram-0.0.13.dist-info/licenses/COPYING
stefano_pytgvoip_pyrogram-0.0.13.dist-info/licenses/COPYING.lesser
stefano_pytgvoip_pyrogram-0.0.13.dist-info/licenses/NOTICE
tgvoip_pyrogram/__init__.py
tgvoip_pyrogram/base_call.py
tgvoip_pyrogram/file_stream_call.py
tgvoip_pyrogram/incoming_call.py
tgvoip_pyrogram/native_io_call.py
tgvoip_pyrogram/outgoing_call.py
tgvoip_pyrogram/service.py
stefano_pytgvoip_pyrogram-0.0.13.dist-info/METADATA
stefano_pytgvoip_pyrogram-0.0.13.dist-info/WHEEL
stefano_pytgvoip_pyrogram-0.0.13.dist-info/top_level.txt
stefano_pytgvoip_pyrogram-0.0.13.dist-info/RECORD
